libertem_asi_tpx3/__init__.py
libertem_asi_tpx3/libertem_asi_tpx3.abi3.so
libertem_asi_tpx3-0.3.0.dist-info/METADATA
libertem_asi_tpx3-0.3.0.dist-info/WHEEL
libertem_asi_tpx3-0.3.0.dist-info/RECORD
