Metadata-Version: 2.4
Name: libertem-asi-tpx3
Version: 0.3.0
Classifier: Programming Language :: Rust
Classifier: Programming Language :: Python :: Implementation :: CPython
Classifier: Programming Language :: Python :: Implementation :: PyPy
Requires-Dist: opentelemetry-api
Requires-Python: >=3.9
Project-URL: repository, https://github.com/LiberTEM/LiberTEM-rs/
